README.md
setup.cfg
setup.py
pytentiostat/__init__.py
pytentiostat/config_reader.py
pytentiostat/main.py
pytentiostat/operator.py
pytentiostat/plotter.py
pytentiostat/reporter.py
pytentiostat/routines.py
pytentiostat.egg-info/PKG-INFO
pytentiostat.egg-info/SOURCES.txt
pytentiostat.egg-info/dependency_links.txt
pytentiostat.egg-info/not-zip-safe
pytentiostat.egg-info/top_level.txt
scripts/pytentiostat