Metadata-Version: 1.0
Name: pytentiostat
Version: 0.0.5
Summary: python API for JUAMI potentiostat
Home-page: https://github.com/juami/pytentiostat
Author: UNKNOWN
Author-email: UNKNOWN
License: UNKNOWN
Platform: UNKNOWN
